digitalhub_ai/__init__.py
digitalhub_ai-0.2.0.dist-info/METADATA
digitalhub_ai-0.2.0.dist-info/WHEEL
digitalhub_ai-0.2.0.dist-info/top_level.txt
digitalhub_ai-0.2.0.dist-info/RECORD
