Metadata-Version: 2.1
Name: digitalhub-ai
Version: 0.2.0
Summary: Python SDK for DHCore
Author-email: Fondazione Bruno Kessler <dslab@fbk.eu>, Matteo Martini <mmartini@fbk.eu>
Keywords: data,dataops,kubernetes
Classifier: License :: OSI Approved :: Apache Software License
Classifier: Programming Language :: Python :: 3.9
Classifier: Programming Language :: Python :: 3.10
Classifier: Programming Language :: Python :: 3.11
Requires-Python: >=3.9
Requires-Dist: digitalhub-core ~=0.2.0
